attention_smithy/__init__.py
attention_smithy/test_functions.py
attention_smithy/utils.py
attention_smithy/attention/HyenaMethod.py
attention_smithy/attention/LinformerAttentionMethod.py
attention_smithy/attention/LongformerAttentionMethod.py
attention_smithy/attention/StandardAttentionMethod.py
attention_smithy/attention/__init__.py
attention_smithy/attention/tests/ManuallyMaskedAttentionMethod.py
attention_smithy/attention/tests/__init__.py
attention_smithy/attention/tests/test_LinformerAttentionMethod.py
attention_smithy/attention/tests/test_LongformerAttentionMethod.py
attention_smithy/attention/tests/test_StandardAttentionMethod.py
attention_smithy/components/Decoder.py
attention_smithy/components/DecoderLayer.py
attention_smithy/components/Encoder.py
attention_smithy/components/EncoderLayer.py
attention_smithy/components/FeedForwardNetwork.py
attention_smithy/components/MultiheadAttention.py
attention_smithy/components/SublayerUnit.py
attention_smithy/components/__init__.py
attention_smithy/components/sublayer_helpers.py
attention_smithy/components/specialized/PerceiverEncoder.py
attention_smithy/components/specialized/PerceiverEncoderLayer.py
attention_smithy/components/specialized/__init__.py
attention_smithy/components/specialized/tests/__init__.py
attention_smithy/components/specialized/tests/test_Perceiver.py
attention_smithy/components/tests/__init__.py
attention_smithy/components/tests/test_Decoder.py
attention_smithy/components/tests/test_DecoderLayer.py
attention_smithy/components/tests/test_Encoder.py
attention_smithy/components/tests/test_EncoderLayer.py
attention_smithy/components/tests/test_FeedForwardNetwork.py
attention_smithy/components/tests/test_MultiheadAttention.py
attention_smithy/components/tests/test_SublayerUnit.py
attention_smithy/generators/BeamGenerator.py
attention_smithy/generators/GeneratorContext.py
attention_smithy/generators/GeneratorModuleAbstractClass.py
attention_smithy/generators/GeneratorStrategy.py
attention_smithy-1.3.0.dist-info/licenses/LICENSE
attention_smithy-1.3.0.dist-info/METADATA
attention_smithy-1.3.0.dist-info/WHEEL
attention_smithy-1.3.0.dist-info/top_level.txt
attention_smithy-1.3.0.dist-info/RECORD
