Metadata-Version: 2.4
Name: attention_smithy
Version: 1.3.0
Author-email: Caleb Cranney <11773171+CCranney@users.noreply.github.com>
Project-URL: Homepage, https://github.com/xomicsdatascience/AttentionSmithy
Project-URL: Bug Tracker, https://github.com/xomicsdatascience/AttentionSmithy/issues
Classifier: Programming Language :: Python :: 3
Classifier: License :: OSI Approved :: MIT License
Classifier: Intended Audience :: Science/Research
Classifier: Topic :: Scientific/Engineering :: Bio-Informatics
Requires-Python: >=3.9
License-File: LICENSE
Requires-Dist: pytorch-lightning>=2.2.1
Requires-Dist: scikit-learn>=1.1.2
Requires-Dist: pandas>=1.2.2
Requires-Dist: rotary-embedding-torch>=0.8.4
Requires-Dist: transformers>=4.47.0
Dynamic: license-file
